<?xml version="1.0" encoding="UTF-8"?>
<PatternInstance
	xmlns:xsi="http://www.w3.org/2001/XMLSchema-instance"
	xsi:schemaLocation="PatternDefinition.xsd"
	name="default-instance"
	description="Descripcion de instance" 
	image="generic.jpg">
	<
	<RelatedFiles name="default-relatedFiles" description="Descripcion de related files" image="generic.jpg">
		<RelatedFile name="Archivo relativo 1" description="Descripcion de archivo relativo 1" reference="../archivo1.java" image="generic.jpg"/>
		<RelatedFile name="Archivo relativo 2" description="Descripcion de archivo relativo 2" reference="../archivo2.java" image="generic.jpg"/>
		<RelatedFile name="Archivo relativo 3" description="Descripcion de archivo relativo 3" reference="../archivo3.java" image="generic.jpg"/>
	</RelatedFiles>
	<Faces image="primefaces.ico">
		<Selection name="default-selection" description="Descripcion de selection" reference="../selection.java"
		insert="true" update="true" delete="true" display="true" image="generic.jpg"/>
		<Register name="default-register" description="Descripcion de register" reference="../register.java" image="generic.jpg"/>
		<Dialog name="default-selection" description="Descripcion de dialog" reference="../dialog.java" image="generic.jpg"/>
	</Faces> 
</PatternInstance>